<?xml version = '1.0' encoding = 'UTF-8'?>
<Diagram class="oracle.dbtools.crest.swingui.relational.DPVRelational" name="Relational_1" id="0A147319-D8B6-E5F3-8E0A-5FD57032A617">
<createdBy>Hargi</createdBy>
<modifiedBy>Hargi</modifiedBy>
<createdTime>2020-11-01 00:44:35 UTC</createdTime>
<autoRoute>false</autoRoute>
<boxInbox>true</boxInbox>
<showLegend>false</showLegend>
<showLabels>false</showLabels>
<showRelAttributes>false</showRelAttributes>
<gridEnabled>false</gridEnabled>
<showGrid>false</showGrid>
<diagramColor>-1</diagramColor>
<display>false</display>
<notation>1</notation>
<objectViews>
<OView class="oracle.dbtools.crest.swingui.relational.TVTable" oid="0B3F5D51-0C0D-4EEB-BBDA-4334E472086B" otype="Table" vid="9F75212F-9CA8-AF1B-867B-0195F30C04B1">
<hideElementsInCurrentOnly>false</hideElementsInCurrentOnly>
<bounds x="488" y="8" width="256" height="154"/>
</OView>
<OView class="oracle.dbtools.crest.swingui.relational.TVTable" oid="0E7F14E7-EC11-424B-B498-887AB5010E25" otype="Table" vid="E3587C06-C1CB-01B2-E69F-DAB526D91075">
<hideElementsInCurrentOnly>false</hideElementsInCurrentOnly>
<bounds x="872" y="501" width="242" height="121"/>
</OView>
<OView class="oracle.dbtools.crest.swingui.relational.TVTable" oid="147813BF-E8BA-E2D4-E178-7ACC6869F981" otype="Table" vid="10636C16-8500-5560-6871-FB8573834554">
<hideElementsInCurrentOnly>false</hideElementsInCurrentOnly>
<bounds x="94" y="11" width="284" height="135"/>
</OView>
<OView class="oracle.dbtools.crest.swingui.relational.TVTable" oid="219A641E-0192-A753-01A8-A0C9C91F6E1E" otype="Table" vid="86E24848-5DB3-5A3F-1D8D-03D14E72B006">
<hideElementsInCurrentOnly>false</hideElementsInCurrentOnly>
<bounds x="63" y="515" width="230" height="135"/>
</OView>
<OView class="oracle.dbtools.crest.swingui.relational.TVTable" oid="2ECE7E49-42F4-6F39-D071-536FBD6915AD" otype="Table" vid="E58FD070-7673-12BC-42B2-8BB4CF44DA94">
<hideElementsInCurrentOnly>false</hideElementsInCurrentOnly>
<bounds x="76" y="213" width="330" height="248"/>
</OView>
<OView class="oracle.dbtools.crest.swingui.relational.TVTable" oid="386C8D8A-589E-860D-5460-EA881A86F3B5" otype="Table" vid="1442892C-5ED2-691E-43F9-87499143A666">
<hideElementsInCurrentOnly>false</hideElementsInCurrentOnly>
<bounds x="822" y="334" width="245" height="94"/>
</OView>
<OView class="oracle.dbtools.crest.swingui.relational.TVTable" oid="3C076246-DF9E-6C20-022D-5A4964EC8B42" otype="Table" vid="A045BBFC-DD66-B4C5-C01E-71C3AD1B3F07">
<hideElementsInCurrentOnly>false</hideElementsInCurrentOnly>
<bounds x="1054" y="28" width="204" height="135"/>
</OView>
<OView class="oracle.dbtools.crest.swingui.relational.TVTable" oid="47B54A9E-6655-C65A-5E6C-AFFE3B9EB796" otype="Table" vid="6D02BE15-3460-A700-BAD8-C3418898E536">
<hideElementsInCurrentOnly>false</hideElementsInCurrentOnly>
<bounds x="554" y="505" width="251" height="114"/>
</OView>
<OView class="oracle.dbtools.crest.swingui.relational.TVTable" oid="4E29BF14-CC9D-5612-FBE9-CBDBFECD7F0A" otype="Table" vid="D398FEB7-2305-98CC-1781-C3B0B1944641">
<hideElementsInCurrentOnly>false</hideElementsInCurrentOnly>
<bounds x="218" y="214" width="125" height="52"/>
</OView>
<OView class="oracle.dbtools.crest.swingui.relational.TVTable" oid="92A29E10-2655-0381-E3FE-45645AC64EE6" otype="Table" vid="DB088046-880B-3F40-B416-81CDB932CA78">
<hideElementsInCurrentOnly>false</hideElementsInCurrentOnly>
<bounds x="789" y="16" width="218" height="143"/>
</OView>
<OView class="oracle.dbtools.crest.swingui.relational.TVTable" oid="9952EF01-F252-75A3-68E5-54854B1DC8EB" otype="Table" vid="2C4B34B4-3C57-32CD-7F2E-9A43B6D4E63D">
<hideElementsInCurrentOnly>false</hideElementsInCurrentOnly>
<bounds x="203" y="288" width="121" height="67"/>
</OView>
<OView class="oracle.dbtools.crest.swingui.relational.TVTable" oid="A1D878F7-D2D1-1CC6-BCB8-57BF1047B511" otype="Table" vid="9E16B790-68CB-C058-8918-339BD535C95E">
<hideElementsInCurrentOnly>false</hideElementsInCurrentOnly>
<bounds x="799" y="212" width="258" height="91"/>
</OView>
<OView class="oracle.dbtools.crest.swingui.relational.TVTable" oid="BDAB10F8-8D1E-32DB-83B6-353266D01B18" otype="Table" vid="EC395971-AEBE-7D82-4CA1-DCEC8A36F5F2">
<hideElementsInCurrentOnly>false</hideElementsInCurrentOnly>
<bounds x="316" y="504" width="226" height="99"/>
</OView>
</objectViews>
<connectors>
<Connector class="oracle.dbtools.crest.swingui.relational.TVFKRelation" oid="143AC9C7-81B6-20E2-C577-80718EEDD94A" otype="FKIndexAssociation" vid_source="1442892C-5ED2-691E-43F9-87499143A666" vid_target="2C4B34B4-3C57-32CD-7F2E-9A43B6D4E63D">
<hideElementsInCurrentOnly>false</hideElementsInCurrentOnly>
<backgroundColor>-16777216</backgroundColor>
<lineWidth>1</lineWidth>
<points>
<point x="822" y="344"/>
<point x="324" y="344"/>
</points>
</Connector>
<Connector class="oracle.dbtools.crest.swingui.relational.TVFKRelation" oid="2547B0B7-03D8-ADC3-7B43-6A0B271F03A9" otype="FKIndexAssociation" vid_source="EC395971-AEBE-7D82-4CA1-DCEC8A36F5F2" vid_target="E58FD070-7673-12BC-42B2-8BB4CF44DA94">
<hideElementsInCurrentOnly>false</hideElementsInCurrentOnly>
<backgroundColor>-16777216</backgroundColor>
<lineWidth>1</lineWidth>
<points>
<point x="432" y="504"/>
<point x="432" y="285"/>
<point x="406" y="285"/>
</points>
</Connector>
<Connector class="oracle.dbtools.crest.swingui.relational.TVFKRelation" oid="29C1A1EE-1536-2EC8-B459-3547306B2F41" otype="FKIndexAssociation" vid_source="E58FD070-7673-12BC-42B2-8BB4CF44DA94" vid_target="E58FD070-7673-12BC-42B2-8BB4CF44DA94">
<hideElementsInCurrentOnly>false</hideElementsInCurrentOnly>
<backgroundColor>-16777216</backgroundColor>
<lineWidth>1</lineWidth>
<points>
<point x="384" y="361"/>
<point x="384" y="358"/>
<point x="384" y="427"/>
<point x="227" y="427"/>
<point x="227" y="461"/>
</points>
</Connector>
<Connector class="oracle.dbtools.crest.swingui.relational.TVFKRelation" oid="3E29200E-F9CF-2F6D-9784-9A744946DE28" otype="FKIndexAssociation" vid_source="10636C16-8500-5560-6871-FB8573834554" vid_target="86E24848-5DB3-5A3F-1D8D-03D14E72B006">
<hideElementsInCurrentOnly>false</hideElementsInCurrentOnly>
<backgroundColor>-16777216</backgroundColor>
<lineWidth>1</lineWidth>
<points>
<point x="208" y="146"/>
<point x="208" y="515"/>
</points>
</Connector>
<Connector class="oracle.dbtools.crest.swingui.relational.TVFKRelation" oid="463D5EBE-AFD9-F718-C1B5-D114569D3AAA" otype="FKIndexAssociation" vid_source="6D02BE15-3460-A700-BAD8-C3418898E536" vid_target="E3587C06-C1CB-01B2-E69F-DAB526D91075">
<hideElementsInCurrentOnly>false</hideElementsInCurrentOnly>
<backgroundColor>-16777216</backgroundColor>
<lineWidth>1</lineWidth>
<points>
<point x="805" y="562"/>
<point x="872" y="562"/>
</points>
</Connector>
<Connector class="oracle.dbtools.crest.swingui.relational.TVFKRelation" oid="57489D5B-E992-DF63-0F16-AB8A4720ACA7" otype="FKIndexAssociation" vid_source="EC395971-AEBE-7D82-4CA1-DCEC8A36F5F2" vid_target="86E24848-5DB3-5A3F-1D8D-03D14E72B006">
<hideElementsInCurrentOnly>false</hideElementsInCurrentOnly>
<backgroundColor>-16777216</backgroundColor>
<lineWidth>1</lineWidth>
<points>
<point x="316" y="559"/>
<point x="293" y="559"/>
</points>
</Connector>
<Connector class="oracle.dbtools.crest.swingui.relational.TVFKRelation" oid="614F00D7-5D77-0B06-8A40-40C0C841D8E3" otype="FKIndexAssociation" vid_source="6D02BE15-3460-A700-BAD8-C3418898E536" vid_target="E58FD070-7673-12BC-42B2-8BB4CF44DA94">
<hideElementsInCurrentOnly>false</hideElementsInCurrentOnly>
<backgroundColor>-16777216</backgroundColor>
<lineWidth>1</lineWidth>
<points>
<point x="601" y="505"/>
<point x="601" y="255"/>
<point x="406" y="255"/>
</points>
</Connector>
<Connector class="oracle.dbtools.crest.swingui.relational.TVFKRelation" oid="619D8DB5-AFB5-3737-F966-4A0970E934A9" otype="FKIndexAssociation" vid_source="10636C16-8500-5560-6871-FB8573834554" vid_target="E58FD070-7673-12BC-42B2-8BB4CF44DA94">
<hideElementsInCurrentOnly>false</hideElementsInCurrentOnly>
<backgroundColor>-16777216</backgroundColor>
<lineWidth>1</lineWidth>
<points>
<point x="236" y="146"/>
<point x="236" y="213"/>
</points>
</Connector>
<Connector class="oracle.dbtools.crest.swingui.relational.TVFKRelation" oid="62932EA5-18F5-239B-EEB7-26471B98B455" otype="FKIndexAssociation" vid_source="9E16B790-68CB-C058-8918-339BD535C95E" vid_target="D398FEB7-2305-98CC-1781-C3B0B1944641">
<hideElementsInCurrentOnly>false</hideElementsInCurrentOnly>
<backgroundColor>-16777216</backgroundColor>
<lineWidth>1</lineWidth>
<points>
<point x="799" y="240"/>
<point x="343" y="240"/>
</points>
</Connector>
<Connector class="oracle.dbtools.crest.swingui.relational.TVFKRelation" oid="A3D5E005-D035-7BC4-F207-64D14526FBB6" otype="FKIndexAssociation" vid_source="E58FD070-7673-12BC-42B2-8BB4CF44DA94" vid_target="D398FEB7-2305-98CC-1781-C3B0B1944641">
<hideElementsInCurrentOnly>false</hideElementsInCurrentOnly>
<backgroundColor>-16777216</backgroundColor>
<lineWidth>1</lineWidth>
<points>
<point x="406" y="240"/>
<point x="218" y="240"/>
</points>
</Connector>
<Connector class="oracle.dbtools.crest.swingui.relational.TVFKRelation" oid="A54AC5B2-2F13-B6CF-A59B-7D8741A4EF74" otype="FKIndexAssociation" vid_source="EC395971-AEBE-7D82-4CA1-DCEC8A36F5F2" vid_target="6D02BE15-3460-A700-BAD8-C3418898E536">
<hideElementsInCurrentOnly>false</hideElementsInCurrentOnly>
<backgroundColor>-16777216</backgroundColor>
<lineWidth>1</lineWidth>
<points>
<point x="542" y="554"/>
<point x="554" y="554"/>
</points>
</Connector>
<Connector class="oracle.dbtools.crest.swingui.relational.TVFKRelation" oid="AD6D381B-D547-C40A-CD29-D86DFD674530" otype="FKIndexAssociation" vid_source="9F75212F-9CA8-AF1B-867B-0195F30C04B1" vid_target="10636C16-8500-5560-6871-FB8573834554">
<hideElementsInCurrentOnly>false</hideElementsInCurrentOnly>
<backgroundColor>-16777216</backgroundColor>
<lineWidth>1</lineWidth>
<points>
<point x="488" y="93"/>
<point x="378" y="93"/>
</points>
</Connector>
<Connector class="oracle.dbtools.crest.swingui.relational.TVFKRelation" oid="ADD76E69-F448-59C6-CDA8-F5C888620F19" otype="FKIndexAssociation" vid_source="A045BBFC-DD66-B4C5-C01E-71C3AD1B3F07" vid_target="DB088046-880B-3F40-B416-81CDB932CA78">
<hideElementsInCurrentOnly>false</hideElementsInCurrentOnly>
<backgroundColor>-16777216</backgroundColor>
<lineWidth>1</lineWidth>
<points>
<point x="1054" y="93"/>
<point x="1007" y="93"/>
</points>
</Connector>
<Connector class="oracle.dbtools.crest.swingui.relational.TVFKRelation" oid="B7548A65-C6B8-297D-F725-4C427E9DA18C" otype="FKIndexAssociation" vid_source="10636C16-8500-5560-6871-FB8573834554" vid_target="86E24848-5DB3-5A3F-1D8D-03D14E72B006">
<hideElementsInCurrentOnly>false</hideElementsInCurrentOnly>
<backgroundColor>-16777216</backgroundColor>
<lineWidth>1</lineWidth>
<points>
<point x="94" y="42"/>
<point x="56" y="42"/>
<point x="51" y="540"/>
<point x="63" y="540"/>
</points>
</Connector>
<Connector class="oracle.dbtools.crest.swingui.relational.TVFKRelation" oid="D8279AA8-6179-53C6-E08B-28CA9CDF3E68" otype="FKIndexAssociation" vid_source="DB088046-880B-3F40-B416-81CDB932CA78" vid_target="9F75212F-9CA8-AF1B-867B-0195F30C04B1">
<hideElementsInCurrentOnly>false</hideElementsInCurrentOnly>
<backgroundColor>-16777216</backgroundColor>
<lineWidth>1</lineWidth>
<points>
<point x="789" y="102"/>
<point x="744" y="102"/>
</points>
</Connector>
<Connector class="oracle.dbtools.crest.swingui.relational.TVFKRelation" oid="FF5F4CAB-40CF-31A6-3377-EB67FFC84446" otype="FKIndexAssociation" vid_source="E58FD070-7673-12BC-42B2-8BB4CF44DA94" vid_target="2C4B34B4-3C57-32CD-7F2E-9A43B6D4E63D">
<hideElementsInCurrentOnly>false</hideElementsInCurrentOnly>
<backgroundColor>-16777216</backgroundColor>
<lineWidth>1</lineWidth>
<points>
<point x="406" y="321"/>
<point x="203" y="321"/>
</points>
</Connector>
</connectors>
<arcs>
<Arc class="oracle.dbtools.crest.swingui.relational.TVFKArc" oid="4D895D27-0AC7-177F-35C6-0603CE66D9FF" otype="FKArc" vid="F9AF0217-A9DC-C3E5-6674-740B439AB77F">
<hideElementsInCurrentOnly>false</hideElementsInCurrentOnly>
<bounds x="56" y="193" width="370" height="288"/>
</Arc>
</arcs>
</Diagram>